rannotation/__init__.py
rannotation/annotate.py
rannotation/core.py
rannotation/helpers.py
rannotation/label_objects.py
rannotation-0.1.dist-info/METADATA
rannotation-0.1.dist-info/WHEEL
rannotation-0.1.dist-info/entry_points.txt
rannotation-0.1.dist-info/top_level.txt
rannotation-0.1.dist-info/RECORD
